{"v0aznVfaNv0IXpJL3ihSQw==":"potenspring.png","/6iKLRN5iQvQfP0hpJp30g==":"dsc02452.jpg","DxfW/OENXhpI2LrzI0+YGg==":"img-7754.jpg","6Y0r7AKay8b/bY6hT+ojuw==":"team1.jpg","hgBd2Jx50aJ7UHK5Nnz2Ng==":"team2.jpg","oRykAiO0rUD++7AmPeEwUg==":"background1.jpg","GZQxnb1rCTZ+1lhCRHLQHA==":"team3.jpg","Wj0P23Hw555xIH8VHoMhzA==":"antonin.png","9VwjktGP0eY3Bmsxv+erVQ==":"isaac.png","tIuP4uYkJRvLAS+hYAFBMg==":"james.png","usehLQKDdeNzalaODuRJEQ==":"ruhi.png","oNT9k0tlk9CZb7bhEcN+wQ==":"saniyah.png","VYY36VLl09KUafl/Sw3n9w==":"sophia.png","8e40mh0vRlcKK07GjwP98A==":"whatsapp-image-2022-01-19-at-7.20.16-pm.jpeg","lu9IKWi8KGwQ/5o1Q6UfPw==":"whatsapp-image-2022-01-19-at-7.20.16-pm-1.jpeg","On4Eoxxk7z9lJ9QJdQtPcg==":"medtroniclogo.png","8eizdvWpbc/E3RmI55jroQ==":"abflogo.jpeg","wlSBY/kMTAm09aDiYVcHXg==":"abflogo-1.jpeg","coYSlzNSFHgxXJblipXsrQ==":"fortekaratelogo.jpeg","in75ZezdY3dVERA+y7Pxuw==":"kowalskislogo.jpeg","hFNzuvH83zqDvIL/iaDIPg==":"medtroniclogo-1.png","M6LzMc5x+pNPEsTbim6aLA==":"abflogo-2.jpeg","EiUZAMkFodEjVBBVm/duBg==":"abflogo-3.jpeg","s/ELuHwtUkY7IbscCaeJIQ==":"kowalskislogo-1.jpeg","kvHVGG/kBlWY+4b54NWhSQ==":"fortekaratelogo-1.jpeg","4t5MTpRH+1RjQubRWOITBQ==":"3.png","5vf7VBsk23EgFkW3KBwFrg==":"2.png","QkE7vgi4E3gen2wE2Gfwfw==":"5.png","YnRSnEk0KHU+nmLnM5Im/Q==":"4.png","FDSJUaPIE9eEd3j3RlvweA==":"sponconmeet.jpeg","1ruj8nZzXwhot8Ggxt9guw==":"sponcon2.jpeg","vWu/8aQDJpdO5mSG6tWNEw==":"kowalskisfundraise.png","rb1qYV7I62S3dK0v+wSuEg==":"fa835342-6e75-4553-9382-808f1083e715.png","Yc59b9YzXm1+DSeWB9H6zw==":"fa835342-6e75-4553-9382-808f1083e715-1.png","02uJarvYeptdH7Bssdgfyw==":"screen-shot-2022-01-28-at-8.45.04-pm.png","KnBi/DOZ0GcBIsBM1rJyRQ==":"screen-shot-2022-01-29-at-1.36.41-pm.png","IdlCvMwYYSXodOhQkVl3XA==":"3e9c7b07-b351-4427-9536-8b77e6220f4f.jpg","cBlAWDTs55rr3UooDIvCJg==":"09d1434f-de2c-47eb-8c7c-df1cdaa9465e.jpg","ONNnwwL0SGcY1lu5hzG+mg==":"img-2129-666x614.jpg","Vb7GgbMoe0curpGYBParsg==":"background3.jpg","nAYnT68kASBtX3JrDD1kSA==":"img-2125-696x732.jpeg","yHYZtAgUuJsC2Pkf64Pcsw==":"img-2127-696x726.jpg","05gaoIYY6YcStwvaCI+Bmw==":"potenlogo.png","9AhkykxjnednUyK+yvgpTg==":"potenlogo-1.png","oJfziEkKccy2QNvarMHb8Q==":"20220110-173535.jpg","/bfpElaI6svXTL+eHJemXQ==":"20220112-173035.jpg","HVufOKJW7tAyIDNjXtVxeg==":"20220112-173115.jpg","Uxw4kSY7GqOZxemcuyCrMw==":"20220105-170506.jpg","e9GMOedAXdhUds2CgHmpRQ==":"20220105-170446.jpeg","WqimXJtbSRB7/zaRU0vdqA==":"20220105-170447.jpeg","Y5JmZMlsEGxnjCMBbUHqsQ==":"20220105-170448.jpeg","oKQ2pIyz05FWw3LDrDvLVg==":"20220105-170449.jpeg","7j3nO2MduNrSWEnzxZXQFQ==":"img-1121.jpg","33gn97Qb4rvFf+ZuGmkdNQ==":"20220102-171028.jpg","Do0LKuOIE/Y29Vje2tyhMw==":"20220102-171113.jpg","OFDKu4p3NkFaUyHCXITyLg==":"dan-holmdahl-eos-r-2022-01-23-15-44-52.jpeg","eGYlWnmnwsnbaVzDTTG4/A==":"dan-holmdahl-eos-r-2022-01-23-15-28-48.jpeg","LZlU1B5rKOtMqxZutEjydg==":"img-1177.jpg","8r852pRK/JoT/nE/Y0G1NQ==":"img-1177.jpeg","8Xhr0C0Yg9KxaoiPSdB5Tg==":"img-1178.jpeg","1qZsdbSlCaOpi6B/o+p/jw==":"img-1179.jpeg","y1m8cG2PhsxKURxwLu37cA==":"img-1180.jpeg","pjNKF61hki/eh3pt+2t5pg==":"img-1181.jpeg","DeZTu4Ye8obU8OJHXx8Esw==":"img-1182.jpeg","dr577utQnTaDL4GCC+6aIg==":"img-1183.jpeg","8oeRXPCsw667pbG5qWyxww==":"img-1184.jpeg","aJuDzJ8CA/prJHvPC+Dg0w==":"img-1185.jpeg","4mStJi9KwkSMyVSg7ScHZQ==":"img-1186.jpeg","Dkdof6lRs3/aLd/DHjZ4Bg==":"img-1187.jpeg","Y+bEyBA14PPyRe3u7YDWWA==":"dan-holmdahl-eos-r-2022-01-23-15-28.jpeg","1IkXai5AOP4xcvJOy4eCkw==":"dan-holmdahl-eos-r-2022-01-23-15-44.jpeg","Sp6fxjVnZboyMqG9mCLp4w==":"state-team-pic.jpeg","eKqr823YaFer962V8vmFdQ==":"state-team-pic-1.jpeg","G2THle6+iyFjc0T/m5Iu8A==":"state-team-pic-2.jpeg","kvopbteCtd3hwT9ULV8jwg==":"state-team-pic-3.jpeg","loCsTgUogw2T890mwNVnJQ==":"state-team-pic-4.jpeg","DfRZf/pjwB1z0p7NgnS2qA==":"state-team-pic-5.jpeg","hrGdvPlX4psKUIEKXqWJZg==":"1.png","e1JqJVsepuTYybzQ5hRYlQ==":"1-1.png","hmaoQ0esdVcKkTSBlmr8HQ==":"3.png"}